flask_marshmallow/__init__.py
flask_marshmallow/compat.py
flask_marshmallow/fields.py
flask_marshmallow/schema.py
flask_marshmallow/sqla.py
flask_marshmallow_b7-0.9.2.dist-info/DESCRIPTION.rst
flask_marshmallow_b7-0.9.2.dist-info/METADATA
flask_marshmallow_b7-0.9.2.dist-info/RECORD
flask_marshmallow_b7-0.9.2.dist-info/WHEEL
flask_marshmallow_b7-0.9.2.dist-info/metadata.json
flask_marshmallow_b7-0.9.2.dist-info/top_level.txt
