Metadata-Version: 2.0
Name: flask-marshmallow-b7
Version: 0.9.2
Summary: Flask + marshmallow for beautiful APIs
Home-page: UNKNOWN
Author: UNKNOWN
Author-email: UNKNOWN
License: Copyright 2014-2017 Steven Loria and contributors
Requires-Dist: Flask
Requires-Dist: marshmallow (>=3.0.0b7)
Requires-Dist: six (>=1.9.0)
